maybankforme/__init__.py
maybankforme/_version.py
maybankforme/main.py
maybankforme/process_transaction.py
maybankforme/common/__init__.py
maybankforme/common/pdf_convert_txt.py
maybankforme/common/txt_convert_csv.py
maybankforme/common/utils.py
maybankforme-1.5.1.dist-info/METADATA
maybankforme-1.5.1.dist-info/WHEEL
maybankforme-1.5.1.dist-info/entry_points.txt
maybankforme-1.5.1.dist-info/top_level.txt
maybankforme-1.5.1.dist-info/RECORD
