Metadata-Version: 2.2
Name: maybankforme
Version: 1.5.1
Summary: This projects converts maybank credit card statement pdf files to a single csv file that allows to be ingestable in other workflow.
Author-email: Zharif Zakaria <z@zhrif.com>
License: MIT
Project-URL: Homepage, https://github.com/zhrif/maybankforme
Project-URL: Documentation, https://github.com/zhrif/maybankforme/tree/main#maybankforme
Project-URL: Repository, https://github.com/zhrif/maybankforme
Project-URL: Changelog, https://github.com/zhrif/maybankforme/releases
Keywords: cli,tool
Classifier: Development Status :: 4 - Beta
Classifier: Programming Language :: Python :: 3
Classifier: Programming Language :: Python :: 3.8
Classifier: Programming Language :: Python :: 3.9
Classifier: Programming Language :: Python :: 3.10
Classifier: Programming Language :: Python :: 3.11
Requires-Python: >=3.8
Requires-Dist: pypdf
Requires-Dist: cryptography>=3.1
Provides-Extra: dev
Requires-Dist: pytest>=7.0; extra == "dev"
Requires-Dist: black>=23.3.0; extra == "dev"
Requires-Dist: flake8>=6.0.0; extra == "dev"
Requires-Dist: mypy>=1.0.0; extra == "dev"
Provides-Extra: test
Requires-Dist: pytest-cov>=4.0.0; extra == "test"
Requires-Dist: tox>=4.0.0; extra == "test"
